{
  "assignee": {
    "type": "unassigned"
  },
  "blocked_at": null,
  "blocked_by": null,
  "blocked_phase": null,
  "blocked_reason": null,
  "branch_name": null,
  "cancelled": false,
  "checklist": [],
  "complexity": "medium",
  "deadline": null,
  "dependencies": [],
  "description": "In phase_executor.rs, update the executor entry point (line ~1255):\n\n1. Phase definition lookup (line ~1263): Check workflow_config.config.phase_definitions first, fall back to runtime_loaded.config.phase_execution()\n\n2. Agent profile merge: Merge workflow config agent_profiles into mutable copy of runtime config agents, so all existing accessor methods (phase_system_prompt, phase_tool_override, etc.) work unchanged\n\n3. Tools allowlist: Combine workflow_config.tools_allowlist + runtime_config.tools_allowlist when calling run_workflow_phase_with_command()\n\nThis keeps the execution layer changes minimal — just the entry point lookup.",
  "estimated_effort": null,
  "id": "TASK-193",
  "impact_area": [],
  "linked_architecture_entities": [],
  "linked_requirements": [],
  "metadata": {
    "completed_at": "2026-03-02T19:10:42.806865Z",
    "created_at": "2026-03-02T16:56:55.380976Z",
    "created_by": "ao-cli",
    "started_at": null,
    "updated_at": "2026-03-02T19:10:42.806866Z",
    "updated_by": "ao-cli",
    "version": 3
  },
  "paused": false,
  "priority": "high",
  "resource_requirements": {
    "max_cpu_percent": null,
    "max_memory_mb": null,
    "requires_network": true
  },
  "risk": "medium",
  "scope": "medium",
  "status": "done",
  "tags": [],
  "title": "Update phase executor lookup to check workflow config first",
  "type": "feature",
  "workflow_metadata": {
    "requires_architecture": false,
    "requires_design": false,
    "requires_production_deploy": false,
    "requires_qa": true,
    "requires_staging_deploy": false,
    "workflow_id": null
  },
  "worktree_path": null
}