{
  "assignee": {
    "type": "human",
    "user_id": "samishukri"
  },
  "blocked_at": null,
  "blocked_by": null,
  "blocked_phase": null,
  "blocked_reason": null,
  "branch_name": null,
  "cancelled": false,
  "checklist": [],
  "complexity": "medium",
  "deadline": null,
  "dependencies": [],
  "description": "The oai-runner's `search_files` tool implementation does a naive `grep -rn` from the project root without excluding build directories (`target/`, `.git/`, `node_modules/`, etc.). This causes it to hang for minutes scanning gigabytes of compiled artifacts.\n\nObserved: `grep -rn --color=never -E planning_shared\\.rs /Users/samishukri/ao-cli/.` ran for 4+ minutes stuck in `target/`.\n\n**Preferred fix**: Switch to `rg` (ripgrep) which respects `.gitignore` by default, providing automatic exclusion of `target/`, `.git/`, `node_modules/`, and any other gitignored paths. If `rg` is not available, fall back to `grep` with `--exclude-dir` flags for common large directories.\n\nKey file: `crates/oai-runner/` — find the search_files tool implementation and make search gitignore-aware.",
  "estimated_effort": null,
  "id": "TASK-218",
  "impact_area": [],
  "linked_architecture_entities": [],
  "linked_requirements": [],
  "metadata": {
    "completed_at": "2026-03-03T05:29:16.746112Z",
    "created_at": "2026-03-02T20:33:18.909494Z",
    "created_by": "ao-cli",
    "started_at": "2026-03-03T05:21:18.757588Z",
    "updated_at": "2026-03-03T05:29:16.746114Z",
    "updated_by": "samishukri",
    "version": 5
  },
  "paused": false,
  "priority": "high",
  "resource_requirements": {
    "max_cpu_percent": null,
    "max_memory_mb": null,
    "requires_network": true
  },
  "risk": "medium",
  "scope": "medium",
  "status": "done",
  "tags": [],
  "title": "Fix oai-runner search_files tool to exclude target/ and .git/ directories",
  "type": "bugfix",
  "workflow_metadata": {
    "requires_architecture": false,
    "requires_design": false,
    "requires_production_deploy": false,
    "requires_qa": true,
    "requires_staging_deploy": false,
    "workflow_id": null
  },
  "worktree_path": null
}