{
  "assignee": {
    "type": "unassigned"
  },
  "blocked_at": null,
  "blocked_by": null,
  "blocked_phase": null,
  "blocked_reason": null,
  "branch_name": "ao/task-007",
  "cancelled": false,
  "checklist": [],
  "complexity": "medium",
  "deadline": null,
  "dependencies": [],
  "description": "Add automated policy checks and docs updates to enforce Rust-only dependency boundaries.",
  "estimated_effort": null,
  "id": "TASK-007",
  "impact_area": [],
  "linked_architecture_entities": [],
  "linked_requirements": [],
  "metadata": {
    "completed_at": "2026-02-25T23:56:18.458390Z",
    "created_at": "2026-02-24T19:48:30.630741Z",
    "created_by": "ao-cli",
    "started_at": "2026-02-25T03:27:07.612244Z",
    "updated_at": "2026-02-25T23:56:18.458393Z",
    "updated_by": "ao-daemon",
    "version": 14
  },
  "paused": false,
  "priority": "high",
  "resource_requirements": {
    "max_cpu_percent": null,
    "max_memory_mb": null,
    "requires_network": true
  },
  "risk": "medium",
  "scope": "medium",
  "status": "done",
  "tags": [],
  "title": "Implement dependency policy checks for Rust-only guardrail",
  "type": "chore",
  "workflow_metadata": {
    "requires_architecture": false,
    "requires_design": false,
    "requires_production_deploy": false,
    "requires_qa": true,
    "requires_staging_deploy": false,
    "workflow_id": null
  },
  "worktree_path": "/Users/samishukri/.ao/ao-cli-1222ef9c4f94/worktrees/task-task-007"
}